odoo/addons/stock_barcodes_picking_batch/README.rst
odoo/addons/stock_barcodes_picking_batch/__init__.py
odoo/addons/stock_barcodes_picking_batch/__manifest__.py
odoo/addons/stock_barcodes_picking_batch/data/stock_barcodes_action.xml
odoo/addons/stock_barcodes_picking_batch/i18n/es.po
odoo/addons/stock_barcodes_picking_batch/i18n/it.po
odoo/addons/stock_barcodes_picking_batch/i18n/stock_barcodes_picking_batch.pot
odoo/addons/stock_barcodes_picking_batch/models/__init__.py
odoo/addons/stock_barcodes_picking_batch/models/stock_picking_batch.py
odoo/addons/stock_barcodes_picking_batch/readme/CONTRIBUTORS.rst
odoo/addons/stock_barcodes_picking_batch/readme/DESCRIPTION.rst
odoo/addons/stock_barcodes_picking_batch/readme/USAGE.rst
odoo/addons/stock_barcodes_picking_batch/security/ir.model.access.csv
odoo/addons/stock_barcodes_picking_batch/static/description/icon.png
odoo/addons/stock_barcodes_picking_batch/static/description/index.html
odoo/addons/stock_barcodes_picking_batch/static/src/js/barcodes_models_mixin.js
odoo/addons/stock_barcodes_picking_batch/tests/__init__.py
odoo/addons/stock_barcodes_picking_batch/tests/test_stock_barcodes_picking_batch.py
odoo/addons/stock_barcodes_picking_batch/views/stock_picking_batch_views.xml
odoo/addons/stock_barcodes_picking_batch/wizard/__init__.py
odoo/addons/stock_barcodes_picking_batch/wizard/stock_barcodes_read_picking_batch.py
odoo/addons/stock_barcodes_picking_batch/wizard/stock_barcodes_read_picking_batch_views.xml
odoo14_addon_stock_barcodes_picking_batch-14.0.1.0.1.dev6.dist-info/METADATA
odoo14_addon_stock_barcodes_picking_batch-14.0.1.0.1.dev6.dist-info/WHEEL
odoo14_addon_stock_barcodes_picking_batch-14.0.1.0.1.dev6.dist-info/top_level.txt
odoo14_addon_stock_barcodes_picking_batch-14.0.1.0.1.dev6.dist-info/RECORD
